advanced_face_age_recognition_module-1.0.0.dist-info/licenses/LICENSE
afads/__init__.py
afads/afads.py
afads/extras/afads_server.py
afads/extras/afads_webcam_consent.py
afads/extras/pygame_webcam.py
advanced_face_age_recognition_module-1.0.0.dist-info/METADATA
advanced_face_age_recognition_module-1.0.0.dist-info/WHEEL
advanced_face_age_recognition_module-1.0.0.dist-info/top_level.txt
advanced_face_age_recognition_module-1.0.0.dist-info/RECORD
