Metadata-Version: 2.4
Name: advanced-face-age-recognition-module
Version: 1.0.0
Summary: AFADS: on-device face age estimation with simple 18+ gating, Tkinter/Pygame/Webcam demos
Author: Your Name
License: MIT
Project-URL: Homepage, https://example.com/afads
Project-URL: Issues, https://example.com/afads/issues
Keywords: face,age,estimation,verification,AFADS
Classifier: Programming Language :: Python :: 3
Classifier: License :: OSI Approved :: MIT License
Classifier: Operating System :: OS Independent
Classifier: Topic :: Security
Classifier: Topic :: Scientific/Engineering :: Artificial Intelligence
Requires-Python: >=3.9
License-File: LICENSE
Requires-Dist: insightface>=0.7.3
Requires-Dist: onnxruntime>=1.17.0
Requires-Dist: opencv-python>=4.9.0.80
Requires-Dist: numpy>=1.26.0
Requires-Dist: fastapi>=0.111.0
Requires-Dist: uvicorn>=0.30.0
Requires-Dist: pillow>=10.3.0
Requires-Dist: pygame>=2.5.2
Dynamic: license-file
